Metadata-Version: 1.0
Name: people
Version: 0.1.9
Summary: Human Interaction API
Home-page: http://github.com/ChrisWaites/people
Author: Chris Waites
Author-email: cwaites10@gmail.com
License: MIT
Platform: UNKNOWN
